{
  "blocking": {
    "options": {
      "other": {
        "__compat": {
          "mdn_url": "https://adblockplus.org/filters#options",
          "support": {
            "adblock": {
              "version_added": null
            },
            "adblockplus": {
              "version_added": null
            },
            "adguard": {
              "version_added": null
            },
            "ublockorigin": {
              "version_added": null
            }
          },
          "status": {
            "experimental": false,
            "standard_track": true,
            "deprecated": false
          }
        }
      }
    }
  }
}
